paiktj/__init__.py
paiktj/csv.py
paiktj/encrypt.py
paiktj/matplotlib.py
paiktj/memory.py
paiktj/multiprocessing.py
paiktj/tf_gpu_setting.py
paiktj/utils.py
paiktj-0.0.9.dist-info/LICENSE
paiktj-0.0.9.dist-info/METADATA
paiktj-0.0.9.dist-info/WHEEL
paiktj-0.0.9.dist-info/top_level.txt
paiktj-0.0.9.dist-info/RECORD
