Metadata-Version: 2.1
Name: paiktj
Version: 0.0.9
Summary: slight variation from builtin modules
Home-page: UNKNOWN
Author: paiktj
Author-email: paiktj@snu.ac.kr
License: BSD
Platform: UNKNOWN
Classifier: Programming Language :: Python :: 3
Classifier: License :: OSI Approved :: BSD License
Classifier: Operating System :: Unix
Requires-Python: >=3
Requires-Dist: numpy (>=1.17)
Requires-Dist: scikit-learn (>=0.16)
Requires-Dist: scipy (>=0.19)
Requires-Dist: matplotlib (>=3.1)
Requires-Dist: cryptography (>=2.0)
Requires-Dist: seaborn (>=0.10)
Requires-Dist: tqdm (>=4.46)
